gwaslab_agent/__init__.py
gwaslab_agent/sumstat_agent.py
gwaslab_agent/agents/__init__.py
gwaslab_agent/agents/a_loader.py
gwaslab_agent/agents/a_loader_summarizer.py
gwaslab_agent/agents/a_path_manager.py
gwaslab_agent/agents/a_planner.py
gwaslab_agent/agents/a_router.py
gwaslab_agent/agents/a_script_fixer.py
gwaslab_agent/agents/a_summarizer.py
gwaslab_agent/agents/a_validator.py
gwaslab_agent/core/__init__.py
gwaslab_agent/core/g_agent_capabilities.py
gwaslab_agent/core/g_base_agent.py
gwaslab_agent/core/g_console.py
gwaslab_agent/core/g_docstring_parser.py
gwaslab_agent/core/g_errors.py
gwaslab_agent/core/g_image.py
gwaslab_agent/core/g_llm.py
gwaslab_agent/core/g_message_utils.py
gwaslab_agent/core/g_middleware.py
gwaslab_agent/core/g_print.py
gwaslab_agent/core/g_session_state.py
gwaslab_agent/core/g_sys_prompt.py
gwaslab_agent/core/g_version.py
gwaslab_agent/data/__init__.py
gwaslab_agent/data/d_data_registry.py
gwaslab_agent/execution/__init__.py
gwaslab_agent/execution/s_script_execution.py
gwaslab_agent/graph/__init__.py
gwaslab_agent/graph/display_graph.py
gwaslab_agent/graph/g_graph.py
gwaslab_agent/history/__init__.py
gwaslab_agent/history/g_history_manager.py
gwaslab_agent/history/g_history_stages.py
gwaslab_agent/history/g_toolcall_extractor.py
gwaslab_agent/script_library/examples.py
gwaslab_agent/tools/__init__.py
gwaslab_agent/tools/g_build_tools.py
gwaslab_agent/tools/g_toolcall_parser.py
gwaslab_agent/tools/g_tools.py
gwaslab_agent/tools/g_warp_tools_helper.py
gwaslab_agent/tools/g_wrap_tools.py
gwaslab_agent-0.1.0.dist-info/licenses/LICENSE
gwaslab_agent-0.1.0.dist-info/METADATA
gwaslab_agent-0.1.0.dist-info/WHEEL
gwaslab_agent-0.1.0.dist-info/top_level.txt
gwaslab_agent-0.1.0.dist-info/RECORD
