Metadata-Version: 2.4
Name: gwaslab-agent
Version: 0.1.0
Summary: GWASLab Agent
Author-email: Yunye <gwaslab@gmail.com>
License-Expression: GPL-3.0-only
Project-URL: Homepage, https://cloufield.github.io/gwaslab/
Project-URL: Github, https://github.com/Cloufield/gwaslab
Classifier: Programming Language :: Python :: 3
Classifier: Operating System :: OS Independent
Requires-Python: <3.13,>=3.12
License-File: LICENSE
Requires-Dist: gwaslab>=3.6.14
Requires-Dist: json5>=0.12.1
Requires-Dist: langchain>=1.1.3
Requires-Dist: langchain-core>=1.0.3
Requires-Dist: langgraph>=0.2.34
Requires-Dist: langchain-google-genai>=3.0.3
Requires-Dist: langchain-openai>=1.0.3
Requires-Dist: mcp[cli]>=1.13.1
Requires-Dist: openpyxl>=3.1.5
Requires-Dist: rich>=14.1.0
Requires-Dist: tabulate>=0.9.0
Dynamic: license-file
